{"docs":
[
{ "_id" :"triolet_36",
        "code" : "t_b36",
        "campus" : "Triolet",
        "type": "batiment",
        "destination" : "enseignement",
        "annee_construction" : 2019,
        "salles": [{"designation":"A36.03","capacite":120,"type":"amphi","acessibilite":"oui","video":"oui"},
                {"designation":"A36.02","capacite":120,"type":"amphi","acessibilite":"oui","video":"oui"},
                {"designation":"A36.01","capacite":120,"type":"amphi","acessibilite":"oui","video":"oui"},
                {"designation":"TD36.202","capacite":40,"type":"TDInfo","acessibilite":"oui","video":"oui"},
                {"designation":"SC36.04","capacite":80,"type":"amphi","acessibilite":"oui","video":"oui"}]},
{ "_id" :"triolet_16",
        "code" : "t_b16",
        "campus" : "Triolet",
        "type": "batiment",
        "destination" : "enseignement",
        "annee_construction" : 1966,
        "salles": [{"designation":"SC16.03","capacite":120,"type":"amphi","acessibilite":"oui","video":"oui"},
                {"designation":"TD16.02","capacite":18,"type":"TD","acessibilite":"oui","video":"oui"},
                {"designation":"TPDeptInfo","capacite":40,"type":"TDInfo","acessibilite":"oui","video":"oui"},
                {"designation":"TPBio","capacite":40,"type":"TP","acessibilite":"oui","video":"oui"}]},
{ "_id" :"triolet_05",
        "code" : "t_b05",
        "campus" : "Triolet",
        "type": "batiment",
        "destination" : "enseignement",
        "annee_construction" : 1964,
        "salles": [{"designation":"A.02","capacite":275,"type":"amphi","acessibilite":"oui","video":"oui"},
                {"designation":"TD5.125","capacite":20,"type":"TDInfo","acessibilite":"oui","video":"oui"},
                {"designation":"TD5.126","capacite":31,"type":"TDInfo","acessibilite":"oui","video":"oui"},
                {"designation":"TD5.210","capacite":40,"type":"TD","acessibilite":"oui","video":"oui"}]}
]
}